startwork/__init__.py
startwork/main.py
startwork/projects_list.json
startwork/constants/__version__.py
startwork/models/CreateProject.py
startwork/models/DeleteProject.py
startwork/models/GenericProjectActionsModel.py
startwork/models/SelectProject.py
startwork/models/__init__.py
startwork/scripts/try_node.sh
startwork/scripts/try_python.sh
startwork/scripts/work.sh
tests/__init__.py
tests/test_CreateProject.py
tests/test_DeleteProject.py
tests/test_GenericProjectActionsModel.py
tests/test_SelectProject.py
tests/test_end_to_end.py
startwork-0.1.3.dist-info/LICENSE
startwork-0.1.3.dist-info/METADATA
startwork-0.1.3.dist-info/WHEEL
startwork-0.1.3.dist-info/entry_points.txt
startwork-0.1.3.dist-info/top_level.txt
startwork-0.1.3.dist-info/RECORD
