Metadata-Version: 2.1
Name: startwork
Version: 0.1.3
Summary: Small CLI to easier start and swap between projects in different stacks.
Home-page: UNKNOWN
Author: JorbFreire
Author-email: jorbfreire@gmail.com
License: UNKNOWN
Keywords: python,inquirer,cli,dev-tools,tooling
Platform: UNKNOWN
Classifier: Development Status :: 3 - Alpha
Classifier: Intended Audience :: Developers
Classifier: Programming Language :: Python :: 3
Classifier: Operating System :: Unix
License-File: LICENSE
Requires-Dist: inquirer (==3.1.2)
